{"features": [{"properties": {"user": "AbeVonDoom", "source": {"link": "http://instagr.am", "displayName": "Instagram"}, "cluster": null, "text": "Well since I have yet to have posted a damn pic on here mig  @ Borough of Manhattan Community College (BMCC) http://t.co/eTzehiIk", "u_utc": "-18000", "time": "2012-09-18T19:25:59.000Z", "verb": "post"}, "geometry": {"coordinates": [-74.01197433, 40.71789169], "type": "Point"}, "type": "Feature"}], "type": "FeatureCollection"}